MANIFEST.in
README.rst
image_view.py
setup.py
test.bash
image_view.egg-info/PKG-INFO
image_view.egg-info/SOURCES.txt
image_view.egg-info/dependency_links.txt
image_view.egg-info/entry_points.txt
image_view.egg-info/not-zip-safe
image_view.egg-info/top_level.txt
test/16_bit_ascii.pgm
test/16_bit_ascii_without_comments.pgm
test/16_bit_ascii_without_newlines.pgm
test/16_bit_binary.pgm
test/8_bit_binary.pgm
test/python.png