Metadata-Version: 1.1
Name: image-view
Version: 0.3.3
Summary: Displays images (PNM, PNG, JPEG, etc.) conveniently from the terminal.
Home-page: https://github.com/myint/image-view
Author: Steven Myint
Author-email: UNKNOWN
License: Expat License
Keywords: netpbm,pbm,pgm,ppm,pnm
Platform: UNKNOWN
Classifier: Environment :: Console
Classifier: License :: OSI Approved :: MIT License
Classifier: Programming Language :: Python :: 2.7
Classifier: Programming Language :: Python :: 3
Classifier: Programming Language :: Python :: 3.4
